MANIFEST.in
README.md
setup.cfg
setup.py
versioneer.py
sentencecloud/MuseoModerno-Bold.ttf
sentencecloud/__init__.py
sentencecloud/__main__.py
sentencecloud/_version.py
sentencecloud/color_from_image.py
sentencecloud/query_integral_image.c
sentencecloud/stopwords
sentencecloud/tokenization.py
sentencecloud/wordcloud.py
sentencecloud/wordcloud_cli.py
sentencecloud.egg-info/PKG-INFO
sentencecloud.egg-info/SOURCES.txt
sentencecloud.egg-info/dependency_links.txt
sentencecloud.egg-info/entry_points.txt
sentencecloud.egg-info/requires.txt
sentencecloud.egg-info/top_level.txt
test/test_sentencecloud.py
test/test_wordcloud.py
test/test_wordcloud_cli.py