Metadata-Version: 2.1
Name: sentencecloud
Version: 0.0.2
Summary: A little sentence cloud generator
Home-page: https://github.com/eRajsh/sentence_cloud
Author: Rajesh Prabhu
Author-email: 
License: MIT
Platform: UNKNOWN
